<?xml version="1.0" encoding="utf-8"?>
<!-- https://learn.microsoft.com/dotnet/fundamentals/package-validation/diagnostic-ids -->
<Suppressions xmlns:xsi="http://www.w3.org/2001/XMLSchema-instance" xmlns:xsd="http://www.w3.org/2001/XMLSchema">
  <Suppression>
    <DiagnosticId>CP0015</DiagnosticId>
    <Target>M:System.Delegate.#ctor(System.Type,System.String)$0:[T:System.Diagnostics.CodeAnalysis.DynamicallyAccessedMembersAttribute]</Target>
    <Left>net9.0/mscorlib.dll</Left>
    <Right>net10.0/mscorlib.dll</Right>
  </Suppression>
  <Suppression>
    <DiagnosticId>CP0015</DiagnosticId>
    <Target>M:System.Delegate.CreateDelegate(System.Type,System.Type,System.String,System.Boolean,System.Boolean)$1:[T:System.Diagnostics.CodeAnalysis.DynamicallyAccessedMembersAttribute]</Target>
    <Left>net9.0/mscorlib.dll</Left>
    <Right>net10.0/mscorlib.dll</Right>
  </Suppression>
  <Suppression>
    <DiagnosticId>CP0015</DiagnosticId>
    <Target>M:System.Delegate.CreateDelegate(System.Type,System.Type,System.String,System.Boolean)$1:[T:System.Diagnostics.CodeAnalysis.DynamicallyAccessedMembersAttribute]</Target>
    <Left>net9.0/mscorlib.dll</Left>
    <Right>net10.0/mscorlib.dll</Right>
  </Suppression>
  <Suppression>
    <DiagnosticId>CP0015</DiagnosticId>
    <Target>M:System.Delegate.CreateDelegate(System.Type,System.Type,System.String)$1:[T:System.Diagnostics.CodeAnalysis.DynamicallyAccessedMembersAttribute]</Target>
    <Left>net9.0/mscorlib.dll</Left>
    <Right>net10.0/mscorlib.dll</Right>
  </Suppression>
  <Suppression>
    <DiagnosticId>CP0015</DiagnosticId>
    <Target>M:System.MulticastDelegate.#ctor(System.Type,System.String)$0:[T:System.Diagnostics.CodeAnalysis.DynamicallyAccessedMembersAttribute]</Target>
    <Left>net9.0/mscorlib.dll</Left>
    <Right>net10.0/mscorlib.dll</Right>
  </Suppression>
  <Suppression>
    <DiagnosticId>CP0015</DiagnosticId>
    <Target>M:System.Delegate.#ctor(System.Type,System.String)$0:[T:System.Diagnostics.CodeAnalysis.DynamicallyAccessedMembersAttribute]</Target>
    <Left>net9.0/netstandard.dll</Left>
    <Right>net10.0/netstandard.dll</Right>
  </Suppression>
  <Suppression>
    <DiagnosticId>CP0015</DiagnosticId>
    <Target>M:System.Delegate.CreateDelegate(System.Type,System.Type,System.String,System.Boolean,System.Boolean)$1:[T:System.Diagnostics.CodeAnalysis.DynamicallyAccessedMembersAttribute]</Target>
    <Left>net9.0/netstandard.dll</Left>
    <Right>net10.0/netstandard.dll</Right>
  </Suppression>
  <Suppression>
    <DiagnosticId>CP0015</DiagnosticId>
    <Target>M:System.Delegate.CreateDelegate(System.Type,System.Type,System.String,System.Boolean)$1:[T:System.Diagnostics.CodeAnalysis.DynamicallyAccessedMembersAttribute]</Target>
    <Left>net9.0/netstandard.dll</Left>
    <Right>net10.0/netstandard.dll</Right>
  </Suppression>
  <Suppression>
    <DiagnosticId>CP0015</DiagnosticId>
    <Target>M:System.Delegate.CreateDelegate(System.Type,System.Type,System.String)$1:[T:System.Diagnostics.CodeAnalysis.DynamicallyAccessedMembersAttribute]</Target>
    <Left>net9.0/netstandard.dll</Left>
    <Right>net10.0/netstandard.dll</Right>
  </Suppression>
  <Suppression>
    <DiagnosticId>CP0015</DiagnosticId>
    <Target>M:System.MulticastDelegate.#ctor(System.Type,System.String)$0:[T:System.Diagnostics.CodeAnalysis.DynamicallyAccessedMembersAttribute]</Target>
    <Left>net9.0/netstandard.dll</Left>
    <Right>net10.0/netstandard.dll</Right>
  </Suppression>
  <Suppression>
    <DiagnosticId>CP0015</DiagnosticId>
    <Target>M:System.Delegate.#ctor(System.Type,System.String)$0:[T:System.Diagnostics.CodeAnalysis.DynamicallyAccessedMembersAttribute]</Target>
    <Left>net9.0/System.Runtime.dll</Left>
    <Right>net10.0/System.Runtime.dll</Right>
  </Suppression>
  <Suppression>
    <DiagnosticId>CP0015</DiagnosticId>
    <Target>M:System.Delegate.CreateDelegate(System.Type,System.Type,System.String,System.Boolean,System.Boolean)$1:[T:System.Diagnostics.CodeAnalysis.DynamicallyAccessedMembersAttribute]</Target>
    <Left>net9.0/System.Runtime.dll</Left>
    <Right>net10.0/System.Runtime.dll</Right>
  </Suppression>
  <Suppression>
    <DiagnosticId>CP0015</DiagnosticId>
    <Target>M:System.Delegate.CreateDelegate(System.Type,System.Type,System.String,System.Boolean)$1:[T:System.Diagnostics.CodeAnalysis.DynamicallyAccessedMembersAttribute]</Target>
    <Left>net9.0/System.Runtime.dll</Left>
    <Right>net10.0/System.Runtime.dll</Right>
  </Suppression>
  <Suppression>
    <DiagnosticId>CP0015</DiagnosticId>
    <Target>M:System.Delegate.CreateDelegate(System.Type,System.Type,System.String)$1:[T:System.Diagnostics.CodeAnalysis.DynamicallyAccessedMembersAttribute]</Target>
    <Left>net9.0/System.Runtime.dll</Left>
    <Right>net10.0/System.Runtime.dll</Right>
  </Suppression>
  <Suppression>
    <DiagnosticId>CP0015</DiagnosticId>
    <Target>M:System.MulticastDelegate.#ctor(System.Type,System.String)$0:[T:System.Diagnostics.CodeAnalysis.DynamicallyAccessedMembersAttribute]</Target>
    <Left>net9.0/System.Runtime.dll</Left>
    <Right>net10.0/System.Runtime.dll</Right>
  </Suppression>
</Suppressions>