<?xml version="1.0" encoding="utf-8"?>
<!-- https://learn.microsoft.com/en-us/dotnet/fundamentals/package-validation/diagnostic-ids -->
<Suppressions xmlns:xsi="http://www.w3.org/2001/XMLSchema-instance" xmlns:xsd="http://www.w3.org/2001/XMLSchema">
  <Suppression>
    <DiagnosticId>CP0014</DiagnosticId>
    <Target>E:System.Diagnostics.Process.ErrorDataReceived:[T:System.ComponentModel.BrowsableAttribute]</Target>
    <Left>netstandard2.1/netstandard.dll</Left>
    <Right>net9.0/netstandard.dll</Right>
  </Suppression>
  <Suppression>
    <DiagnosticId>CP0014</DiagnosticId>
    <Target>E:System.Diagnostics.Process.Exited:[T:System.ComponentModel.CategoryAttribute]</Target>
    <Left>netstandard2.1/netstandard.dll</Left>
    <Right>net9.0/netstandard.dll</Right>
  </Suppression>
  <Suppression>
    <DiagnosticId>CP0014</DiagnosticId>
    <Target>E:System.Diagnostics.Process.OutputDataReceived:[T:System.ComponentModel.BrowsableAttribute]</Target>
    <Left>netstandard2.1/netstandard.dll</Left>
    <Right>net9.0/netstandard.dll</Right>
  </Suppression>
  <Suppression>
    <DiagnosticId>CP0014</DiagnosticId>
    <Target>E:System.IO.FileSystemWatcher.Error:[T:System.ComponentModel.BrowsableAttribute]</Target>
    <Left>netstandard2.1/netstandard.dll</Left>
    <Right>net9.0/netstandard.dll</Right>
  </Suppression>
  <Suppression>
    <DiagnosticId>CP0014</DiagnosticId>
    <Target>E:System.Timers.Timer.Elapsed:[T:System.ComponentModel.CategoryAttribute]</Target>
    <Left>netstandard2.1/netstandard.dll</Left>
    <Right>net9.0/netstandard.dll</Right>
  </Suppression>
  <Suppression>
    <DiagnosticId>CP0014</DiagnosticId>
    <Target>M:System.Security.SecureString.AppendChar(System.Char):[T:System.Runtime.ExceptionServices.HandleProcessCorruptedStateExceptionsAttribute]</Target>
    <Left>netstandard2.1/netstandard.dll</Left>
    <Right>net9.0/netstandard.dll</Right>
  </Suppression>
  <Suppression>
    <DiagnosticId>CP0014</DiagnosticId>
    <Target>M:System.Security.SecureString.InsertAt(System.Int32,System.Char):[T:System.Runtime.ExceptionServices.HandleProcessCorruptedStateExceptionsAttribute]</Target>
    <Left>netstandard2.1/netstandard.dll</Left>
    <Right>net9.0/netstandard.dll</Right>
  </Suppression>
  <Suppression>
    <DiagnosticId>CP0014</DiagnosticId>
    <Target>M:System.Security.SecureString.RemoveAt(System.Int32):[T:System.Runtime.ExceptionServices.HandleProcessCorruptedStateExceptionsAttribute]</Target>
    <Left>netstandard2.1/netstandard.dll</Left>
    <Right>net9.0/netstandard.dll</Right>
  </Suppression>
  <Suppression>
    <DiagnosticId>CP0014</DiagnosticId>
    <Target>M:System.Security.SecureString.SetAt(System.Int32,System.Char):[T:System.Runtime.ExceptionServices.HandleProcessCorruptedStateExceptionsAttribute]</Target>
    <Left>netstandard2.1/netstandard.dll</Left>
    <Right>net9.0/netstandard.dll</Right>
  </Suppression>
  <Suppression>
    <DiagnosticId>CP0014</DiagnosticId>
    <Target>P:System.ComponentModel.BackgroundWorker.CancellationPending:[T:System.ComponentModel.BrowsableAttribute]</Target>
    <Left>netstandard2.1/netstandard.dll</Left>
    <Right>net9.0/netstandard.dll</Right>
  </Suppression>
  <Suppression>
    <DiagnosticId>CP0014</DiagnosticId>
    <Target>P:System.ComponentModel.BackgroundWorker.IsBusy:[T:System.ComponentModel.BrowsableAttribute]</Target>
    <Left>netstandard2.1/netstandard.dll</Left>
    <Right>net9.0/netstandard.dll</Right>
  </Suppression>
  <Suppression>
    <DiagnosticId>CP0014</DiagnosticId>
    <Target>P:System.ComponentModel.BackgroundWorker.WorkerReportsProgress:[T:System.ComponentModel.DefaultValueAttribute]</Target>
    <Left>netstandard2.1/netstandard.dll</Left>
    <Right>net9.0/netstandard.dll</Right>
  </Suppression>
  <Suppression>
    <DiagnosticId>CP0014</DiagnosticId>
    <Target>P:System.ComponentModel.BackgroundWorker.WorkerSupportsCancellation:[T:System.ComponentModel.DefaultValueAttribute]</Target>
    <Left>netstandard2.1/netstandard.dll</Left>
    <Right>net9.0/netstandard.dll</Right>
  </Suppression>
  <Suppression>
    <DiagnosticId>CP0014</DiagnosticId>
    <Target>P:System.ComponentModel.RunWorkerCompletedEventArgs.UserState:[T:System.ComponentModel.BrowsableAttribute]</Target>
    <Left>netstandard2.1/netstandard.dll</Left>
    <Right>net9.0/netstandard.dll</Right>
  </Suppression>
  <Suppression>
    <DiagnosticId>CP0014</DiagnosticId>
    <Target>P:System.Diagnostics.Process.BasePriority:[T:System.ComponentModel.DesignerSerializationVisibilityAttribute]</Target>
    <Left>netstandard2.1/netstandard.dll</Left>
    <Right>net9.0/netstandard.dll</Right>
  </Suppression>
  <Suppression>
    <DiagnosticId>CP0014</DiagnosticId>
    <Target>P:System.Diagnostics.Process.EnableRaisingEvents:[T:System.ComponentModel.BrowsableAttribute]</Target>
    <Left>netstandard2.1/netstandard.dll</Left>
    <Right>net9.0/netstandard.dll</Right>
  </Suppression>
  <Suppression>
    <DiagnosticId>CP0014</DiagnosticId>
    <Target>P:System.Diagnostics.Process.EnableRaisingEvents:[T:System.ComponentModel.DefaultValueAttribute]</Target>
    <Left>netstandard2.1/netstandard.dll</Left>
    <Right>net9.0/netstandard.dll</Right>
  </Suppression>
  <Suppression>
    <DiagnosticId>CP0014</DiagnosticId>
    <Target>P:System.Diagnostics.Process.ExitCode:[T:System.ComponentModel.BrowsableAttribute]</Target>
    <Left>netstandard2.1/netstandard.dll</Left>
    <Right>net9.0/netstandard.dll</Right>
  </Suppression>
  <Suppression>
    <DiagnosticId>CP0014</DiagnosticId>
    <Target>P:System.Diagnostics.Process.ExitCode:[T:System.ComponentModel.DesignerSerializationVisibilityAttribute]</Target>
    <Left>netstandard2.1/netstandard.dll</Left>
    <Right>net9.0/netstandard.dll</Right>
  </Suppression>
  <Suppression>
    <DiagnosticId>CP0014</DiagnosticId>
    <Target>P:System.Diagnostics.Process.ExitTime:[T:System.ComponentModel.BrowsableAttribute]</Target>
    <Left>netstandard2.1/netstandard.dll</Left>
    <Right>net9.0/netstandard.dll</Right>
  </Suppression>
  <Suppression>
    <DiagnosticId>CP0014</DiagnosticId>
    <Target>P:System.Diagnostics.Process.ExitTime:[T:System.ComponentModel.DesignerSerializationVisibilityAttribute]</Target>
    <Left>netstandard2.1/netstandard.dll</Left>
    <Right>net9.0/netstandard.dll</Right>
  </Suppression>
  <Suppression>
    <DiagnosticId>CP0014</DiagnosticId>
    <Target>P:System.Diagnostics.Process.Handle:[T:System.ComponentModel.BrowsableAttribute]</Target>
    <Left>netstandard2.1/netstandard.dll</Left>
    <Right>net9.0/netstandard.dll</Right>
  </Suppression>
  <Suppression>
    <DiagnosticId>CP0014</DiagnosticId>
    <Target>P:System.Diagnostics.Process.Handle:[T:System.ComponentModel.DesignerSerializationVisibilityAttribute]</Target>
    <Left>netstandard2.1/netstandard.dll</Left>
    <Right>net9.0/netstandard.dll</Right>
  </Suppression>
  <Suppression>
    <DiagnosticId>CP0014</DiagnosticId>
    <Target>P:System.Diagnostics.Process.HandleCount:[T:System.ComponentModel.DesignerSerializationVisibilityAttribute]</Target>
    <Left>netstandard2.1/netstandard.dll</Left>
    <Right>net9.0/netstandard.dll</Right>
  </Suppression>
  <Suppression>
    <DiagnosticId>CP0014</DiagnosticId>
    <Target>P:System.Diagnostics.Process.HasExited:[T:System.ComponentModel.BrowsableAttribute]</Target>
    <Left>netstandard2.1/netstandard.dll</Left>
    <Right>net9.0/netstandard.dll</Right>
  </Suppression>
  <Suppression>
    <DiagnosticId>CP0014</DiagnosticId>
    <Target>P:System.Diagnostics.Process.HasExited:[T:System.ComponentModel.DesignerSerializationVisibilityAttribute]</Target>
    <Left>netstandard2.1/netstandard.dll</Left>
    <Right>net9.0/netstandard.dll</Right>
  </Suppression>
  <Suppression>
    <DiagnosticId>CP0014</DiagnosticId>
    <Target>P:System.Diagnostics.Process.Id:[T:System.ComponentModel.DesignerSerializationVisibilityAttribute]</Target>
    <Left>netstandard2.1/netstandard.dll</Left>
    <Right>net9.0/netstandard.dll</Right>
  </Suppression>
  <Suppression>
    <DiagnosticId>CP0014</DiagnosticId>
    <Target>P:System.Diagnostics.Process.MachineName:[T:System.ComponentModel.BrowsableAttribute]</Target>
    <Left>netstandard2.1/netstandard.dll</Left>
    <Right>net9.0/netstandard.dll</Right>
  </Suppression>
  <Suppression>
    <DiagnosticId>CP0014</DiagnosticId>
    <Target>P:System.Diagnostics.Process.MachineName:[T:System.ComponentModel.DesignerSerializationVisibilityAttribute]</Target>
    <Left>netstandard2.1/netstandard.dll</Left>
    <Right>net9.0/netstandard.dll</Right>
  </Suppression>
  <Suppression>
    <DiagnosticId>CP0014</DiagnosticId>
    <Target>P:System.Diagnostics.Process.MainModule:[T:System.ComponentModel.BrowsableAttribute]</Target>
    <Left>netstandard2.1/netstandard.dll</Left>
    <Right>net9.0/netstandard.dll</Right>
  </Suppression>
  <Suppression>
    <DiagnosticId>CP0014</DiagnosticId>
    <Target>P:System.Diagnostics.Process.MainModule:[T:System.ComponentModel.DesignerSerializationVisibilityAttribute]</Target>
    <Left>netstandard2.1/netstandard.dll</Left>
    <Right>net9.0/netstandard.dll</Right>
  </Suppression>
  <Suppression>
    <DiagnosticId>CP0014</DiagnosticId>
    <Target>P:System.Diagnostics.Process.MainWindowHandle:[T:System.ComponentModel.DesignerSerializationVisibilityAttribute]</Target>
    <Left>netstandard2.1/netstandard.dll</Left>
    <Right>net9.0/netstandard.dll</Right>
  </Suppression>
  <Suppression>
    <DiagnosticId>CP0014</DiagnosticId>
    <Target>P:System.Diagnostics.Process.MainWindowTitle:[T:System.ComponentModel.DesignerSerializationVisibilityAttribute]</Target>
    <Left>netstandard2.1/netstandard.dll</Left>
    <Right>net9.0/netstandard.dll</Right>
  </Suppression>
  <Suppression>
    <DiagnosticId>CP0014</DiagnosticId>
    <Target>P:System.Diagnostics.Process.MaxWorkingSet:[T:System.ComponentModel.DesignerSerializationVisibilityAttribute]</Target>
    <Left>netstandard2.1/netstandard.dll</Left>
    <Right>net9.0/netstandard.dll</Right>
  </Suppression>
  <Suppression>
    <DiagnosticId>CP0014</DiagnosticId>
    <Target>P:System.Diagnostics.Process.MinWorkingSet:[T:System.ComponentModel.DesignerSerializationVisibilityAttribute]</Target>
    <Left>netstandard2.1/netstandard.dll</Left>
    <Right>net9.0/netstandard.dll</Right>
  </Suppression>
  <Suppression>
    <DiagnosticId>CP0014</DiagnosticId>
    <Target>P:System.Diagnostics.Process.Modules:[T:System.ComponentModel.BrowsableAttribute]</Target>
    <Left>netstandard2.1/netstandard.dll</Left>
    <Right>net9.0/netstandard.dll</Right>
  </Suppression>
  <Suppression>
    <DiagnosticId>CP0014</DiagnosticId>
    <Target>P:System.Diagnostics.Process.Modules:[T:System.ComponentModel.DesignerSerializationVisibilityAttribute]</Target>
    <Left>netstandard2.1/netstandard.dll</Left>
    <Right>net9.0/netstandard.dll</Right>
  </Suppression>
  <Suppression>
    <DiagnosticId>CP0014</DiagnosticId>
    <Target>P:System.Diagnostics.Process.NonpagedSystemMemorySize:[T:System.ComponentModel.DesignerSerializationVisibilityAttribute]</Target>
    <Left>netstandard2.1/netstandard.dll</Left>
    <Right>net9.0/netstandard.dll</Right>
  </Suppression>
  <Suppression>
    <DiagnosticId>CP0014</DiagnosticId>
    <Target>P:System.Diagnostics.Process.NonpagedSystemMemorySize64:[T:System.ComponentModel.DesignerSerializationVisibilityAttribute]</Target>
    <Left>netstandard2.1/netstandard.dll</Left>
    <Right>net9.0/netstandard.dll</Right>
  </Suppression>
  <Suppression>
    <DiagnosticId>CP0014</DiagnosticId>
    <Target>P:System.Diagnostics.Process.PagedMemorySize:[T:System.ComponentModel.DesignerSerializationVisibilityAttribute]</Target>
    <Left>netstandard2.1/netstandard.dll</Left>
    <Right>net9.0/netstandard.dll</Right>
  </Suppression>
  <Suppression>
    <DiagnosticId>CP0014</DiagnosticId>
    <Target>P:System.Diagnostics.Process.PagedMemorySize64:[T:System.ComponentModel.DesignerSerializationVisibilityAttribute]</Target>
    <Left>netstandard2.1/netstandard.dll</Left>
    <Right>net9.0/netstandard.dll</Right>
  </Suppression>
  <Suppression>
    <DiagnosticId>CP0014</DiagnosticId>
    <Target>P:System.Diagnostics.Process.PagedSystemMemorySize:[T:System.ComponentModel.DesignerSerializationVisibilityAttribute]</Target>
    <Left>netstandard2.1/netstandard.dll</Left>
    <Right>net9.0/netstandard.dll</Right>
  </Suppression>
  <Suppression>
    <DiagnosticId>CP0014</DiagnosticId>
    <Target>P:System.Diagnostics.Process.PagedSystemMemorySize64:[T:System.ComponentModel.DesignerSerializationVisibilityAttribute]</Target>
    <Left>netstandard2.1/netstandard.dll</Left>
    <Right>net9.0/netstandard.dll</Right>
  </Suppression>
  <Suppression>
    <DiagnosticId>CP0014</DiagnosticId>
    <Target>P:System.Diagnostics.Process.PeakPagedMemorySize:[T:System.ComponentModel.DesignerSerializationVisibilityAttribute]</Target>
    <Left>netstandard2.1/netstandard.dll</Left>
    <Right>net9.0/netstandard.dll</Right>
  </Suppression>
  <Suppression>
    <DiagnosticId>CP0014</DiagnosticId>
    <Target>P:System.Diagnostics.Process.PeakPagedMemorySize64:[T:System.ComponentModel.DesignerSerializationVisibilityAttribute]</Target>
    <Left>netstandard2.1/netstandard.dll</Left>
    <Right>net9.0/netstandard.dll</Right>
  </Suppression>
  <Suppression>
    <DiagnosticId>CP0014</DiagnosticId>
    <Target>P:System.Diagnostics.Process.PeakVirtualMemorySize:[T:System.ComponentModel.DesignerSerializationVisibilityAttribute]</Target>
    <Left>netstandard2.1/netstandard.dll</Left>
    <Right>net9.0/netstandard.dll</Right>
  </Suppression>
  <Suppression>
    <DiagnosticId>CP0014</DiagnosticId>
    <Target>P:System.Diagnostics.Process.PeakVirtualMemorySize64:[T:System.ComponentModel.DesignerSerializationVisibilityAttribute]</Target>
    <Left>netstandard2.1/netstandard.dll</Left>
    <Right>net9.0/netstandard.dll</Right>
  </Suppression>
  <Suppression>
    <DiagnosticId>CP0014</DiagnosticId>
    <Target>P:System.Diagnostics.Process.PeakWorkingSet:[T:System.ComponentModel.DesignerSerializationVisibilityAttribute]</Target>
    <Left>netstandard2.1/netstandard.dll</Left>
    <Right>net9.0/netstandard.dll</Right>
  </Suppression>
  <Suppression>
    <DiagnosticId>CP0014</DiagnosticId>
    <Target>P:System.Diagnostics.Process.PeakWorkingSet64:[T:System.ComponentModel.DesignerSerializationVisibilityAttribute]</Target>
    <Left>netstandard2.1/netstandard.dll</Left>
    <Right>net9.0/netstandard.dll</Right>
  </Suppression>
  <Suppression>
    <DiagnosticId>CP0014</DiagnosticId>
    <Target>P:System.Diagnostics.Process.PriorityBoostEnabled:[T:System.ComponentModel.DesignerSerializationVisibilityAttribute]</Target>
    <Left>netstandard2.1/netstandard.dll</Left>
    <Right>net9.0/netstandard.dll</Right>
  </Suppression>
  <Suppression>
    <DiagnosticId>CP0014</DiagnosticId>
    <Target>P:System.Diagnostics.Process.PriorityClass:[T:System.ComponentModel.DesignerSerializationVisibilityAttribute]</Target>
    <Left>netstandard2.1/netstandard.dll</Left>
    <Right>net9.0/netstandard.dll</Right>
  </Suppression>
  <Suppression>
    <DiagnosticId>CP0014</DiagnosticId>
    <Target>P:System.Diagnostics.Process.PrivateMemorySize:[T:System.ComponentModel.DesignerSerializationVisibilityAttribute]</Target>
    <Left>netstandard2.1/netstandard.dll</Left>
    <Right>net9.0/netstandard.dll</Right>
  </Suppression>
  <Suppression>
    <DiagnosticId>CP0014</DiagnosticId>
    <Target>P:System.Diagnostics.Process.PrivateMemorySize64:[T:System.ComponentModel.DesignerSerializationVisibilityAttribute]</Target>
    <Left>netstandard2.1/netstandard.dll</Left>
    <Right>net9.0/netstandard.dll</Right>
  </Suppression>
  <Suppression>
    <DiagnosticId>CP0014</DiagnosticId>
    <Target>P:System.Diagnostics.Process.PrivilegedProcessorTime:[T:System.ComponentModel.DesignerSerializationVisibilityAttribute]</Target>
    <Left>netstandard2.1/netstandard.dll</Left>
    <Right>net9.0/netstandard.dll</Right>
  </Suppression>
  <Suppression>
    <DiagnosticId>CP0014</DiagnosticId>
    <Target>P:System.Diagnostics.Process.ProcessName:[T:System.ComponentModel.DesignerSerializationVisibilityAttribute]</Target>
    <Left>netstandard2.1/netstandard.dll</Left>
    <Right>net9.0/netstandard.dll</Right>
  </Suppression>
  <Suppression>
    <DiagnosticId>CP0014</DiagnosticId>
    <Target>P:System.Diagnostics.Process.ProcessorAffinity:[T:System.ComponentModel.DesignerSerializationVisibilityAttribute]</Target>
    <Left>netstandard2.1/netstandard.dll</Left>
    <Right>net9.0/netstandard.dll</Right>
  </Suppression>
  <Suppression>
    <DiagnosticId>CP0014</DiagnosticId>
    <Target>P:System.Diagnostics.Process.Responding:[T:System.ComponentModel.DesignerSerializationVisibilityAttribute]</Target>
    <Left>netstandard2.1/netstandard.dll</Left>
    <Right>net9.0/netstandard.dll</Right>
  </Suppression>
  <Suppression>
    <DiagnosticId>CP0014</DiagnosticId>
    <Target>P:System.Diagnostics.Process.SafeHandle:[T:System.ComponentModel.BrowsableAttribute]</Target>
    <Left>netstandard2.1/netstandard.dll</Left>
    <Right>net9.0/netstandard.dll</Right>
  </Suppression>
  <Suppression>
    <DiagnosticId>CP0014</DiagnosticId>
    <Target>P:System.Diagnostics.Process.SafeHandle:[T:System.ComponentModel.DesignerSerializationVisibilityAttribute]</Target>
    <Left>netstandard2.1/netstandard.dll</Left>
    <Right>net9.0/netstandard.dll</Right>
  </Suppression>
  <Suppression>
    <DiagnosticId>CP0014</DiagnosticId>
    <Target>P:System.Diagnostics.Process.SessionId:[T:System.ComponentModel.DesignerSerializationVisibilityAttribute]</Target>
    <Left>netstandard2.1/netstandard.dll</Left>
    <Right>net9.0/netstandard.dll</Right>
  </Suppression>
  <Suppression>
    <DiagnosticId>CP0014</DiagnosticId>
    <Target>P:System.Diagnostics.Process.StandardError:[T:System.ComponentModel.BrowsableAttribute]</Target>
    <Left>netstandard2.1/netstandard.dll</Left>
    <Right>net9.0/netstandard.dll</Right>
  </Suppression>
  <Suppression>
    <DiagnosticId>CP0014</DiagnosticId>
    <Target>P:System.Diagnostics.Process.StandardError:[T:System.ComponentModel.DesignerSerializationVisibilityAttribute]</Target>
    <Left>netstandard2.1/netstandard.dll</Left>
    <Right>net9.0/netstandard.dll</Right>
  </Suppression>
  <Suppression>
    <DiagnosticId>CP0014</DiagnosticId>
    <Target>P:System.Diagnostics.Process.StandardInput:[T:System.ComponentModel.BrowsableAttribute]</Target>
    <Left>netstandard2.1/netstandard.dll</Left>
    <Right>net9.0/netstandard.dll</Right>
  </Suppression>
  <Suppression>
    <DiagnosticId>CP0014</DiagnosticId>
    <Target>P:System.Diagnostics.Process.StandardInput:[T:System.ComponentModel.DesignerSerializationVisibilityAttribute]</Target>
    <Left>netstandard2.1/netstandard.dll</Left>
    <Right>net9.0/netstandard.dll</Right>
  </Suppression>
  <Suppression>
    <DiagnosticId>CP0014</DiagnosticId>
    <Target>P:System.Diagnostics.Process.StandardOutput:[T:System.ComponentModel.BrowsableAttribute]</Target>
    <Left>netstandard2.1/netstandard.dll</Left>
    <Right>net9.0/netstandard.dll</Right>
  </Suppression>
  <Suppression>
    <DiagnosticId>CP0014</DiagnosticId>
    <Target>P:System.Diagnostics.Process.StandardOutput:[T:System.ComponentModel.DesignerSerializationVisibilityAttribute]</Target>
    <Left>netstandard2.1/netstandard.dll</Left>
    <Right>net9.0/netstandard.dll</Right>
  </Suppression>
  <Suppression>
    <DiagnosticId>CP0014</DiagnosticId>
    <Target>P:System.Diagnostics.Process.StartInfo:[T:System.ComponentModel.BrowsableAttribute]</Target>
    <Left>netstandard2.1/netstandard.dll</Left>
    <Right>net9.0/netstandard.dll</Right>
  </Suppression>
  <Suppression>
    <DiagnosticId>CP0014</DiagnosticId>
    <Target>P:System.Diagnostics.Process.StartInfo:[T:System.ComponentModel.DesignerSerializationVisibilityAttribute]</Target>
    <Left>netstandard2.1/netstandard.dll</Left>
    <Right>net9.0/netstandard.dll</Right>
  </Suppression>
  <Suppression>
    <DiagnosticId>CP0014</DiagnosticId>
    <Target>P:System.Diagnostics.Process.StartTime:[T:System.ComponentModel.DesignerSerializationVisibilityAttribute]</Target>
    <Left>netstandard2.1/netstandard.dll</Left>
    <Right>net9.0/netstandard.dll</Right>
  </Suppression>
  <Suppression>
    <DiagnosticId>CP0014</DiagnosticId>
    <Target>P:System.Diagnostics.Process.SynchronizingObject:[T:System.ComponentModel.BrowsableAttribute]</Target>
    <Left>netstandard2.1/netstandard.dll</Left>
    <Right>net9.0/netstandard.dll</Right>
  </Suppression>
  <Suppression>
    <DiagnosticId>CP0014</DiagnosticId>
    <Target>P:System.Diagnostics.Process.SynchronizingObject:[T:System.ComponentModel.DefaultValueAttribute]</Target>
    <Left>netstandard2.1/netstandard.dll</Left>
    <Right>net9.0/netstandard.dll</Right>
  </Suppression>
  <Suppression>
    <DiagnosticId>CP0014</DiagnosticId>
    <Target>P:System.Diagnostics.Process.Threads:[T:System.ComponentModel.BrowsableAttribute]</Target>
    <Left>netstandard2.1/netstandard.dll</Left>
    <Right>net9.0/netstandard.dll</Right>
  </Suppression>
  <Suppression>
    <DiagnosticId>CP0014</DiagnosticId>
    <Target>P:System.Diagnostics.Process.Threads:[T:System.ComponentModel.DesignerSerializationVisibilityAttribute]</Target>
    <Left>netstandard2.1/netstandard.dll</Left>
    <Right>net9.0/netstandard.dll</Right>
  </Suppression>
  <Suppression>
    <DiagnosticId>CP0014</DiagnosticId>
    <Target>P:System.Diagnostics.Process.TotalProcessorTime:[T:System.ComponentModel.DesignerSerializationVisibilityAttribute]</Target>
    <Left>netstandard2.1/netstandard.dll</Left>
    <Right>net9.0/netstandard.dll</Right>
  </Suppression>
  <Suppression>
    <DiagnosticId>CP0014</DiagnosticId>
    <Target>P:System.Diagnostics.Process.UserProcessorTime:[T:System.ComponentModel.DesignerSerializationVisibilityAttribute]</Target>
    <Left>netstandard2.1/netstandard.dll</Left>
    <Right>net9.0/netstandard.dll</Right>
  </Suppression>
  <Suppression>
    <DiagnosticId>CP0014</DiagnosticId>
    <Target>P:System.Diagnostics.Process.VirtualMemorySize:[T:System.ComponentModel.DesignerSerializationVisibilityAttribute]</Target>
    <Left>netstandard2.1/netstandard.dll</Left>
    <Right>net9.0/netstandard.dll</Right>
  </Suppression>
  <Suppression>
    <DiagnosticId>CP0014</DiagnosticId>
    <Target>P:System.Diagnostics.Process.VirtualMemorySize64:[T:System.ComponentModel.DesignerSerializationVisibilityAttribute]</Target>
    <Left>netstandard2.1/netstandard.dll</Left>
    <Right>net9.0/netstandard.dll</Right>
  </Suppression>
  <Suppression>
    <DiagnosticId>CP0014</DiagnosticId>
    <Target>P:System.Diagnostics.Process.WorkingSet:[T:System.ComponentModel.DesignerSerializationVisibilityAttribute]</Target>
    <Left>netstandard2.1/netstandard.dll</Left>
    <Right>net9.0/netstandard.dll</Right>
  </Suppression>
  <Suppression>
    <DiagnosticId>CP0014</DiagnosticId>
    <Target>P:System.Diagnostics.Process.WorkingSet64:[T:System.ComponentModel.DesignerSerializationVisibilityAttribute]</Target>
    <Left>netstandard2.1/netstandard.dll</Left>
    <Right>net9.0/netstandard.dll</Right>
  </Suppression>
  <Suppression>
    <DiagnosticId>CP0014</DiagnosticId>
    <Target>P:System.Diagnostics.ProcessModule.FileVersionInfo:[T:System.ComponentModel.BrowsableAttribute]</Target>
    <Left>netstandard2.1/netstandard.dll</Left>
    <Right>net9.0/netstandard.dll</Right>
  </Suppression>
  <Suppression>
    <DiagnosticId>CP0014</DiagnosticId>
    <Target>P:System.Diagnostics.ProcessStartInfo.Arguments:[T:System.ComponentModel.DefaultValueAttribute]</Target>
    <Left>netstandard2.1/netstandard.dll</Left>
    <Right>net9.0/netstandard.dll</Right>
  </Suppression>
  <Suppression>
    <DiagnosticId>CP0014</DiagnosticId>
    <Target>P:System.Diagnostics.ProcessStartInfo.Arguments:[T:System.ComponentModel.NotifyParentPropertyAttribute]</Target>
    <Left>netstandard2.1/netstandard.dll</Left>
    <Right>net9.0/netstandard.dll</Right>
  </Suppression>
  <Suppression>
    <DiagnosticId>CP0014</DiagnosticId>
    <Target>P:System.Diagnostics.ProcessStartInfo.Arguments:[T:System.ComponentModel.SettingsBindableAttribute]</Target>
    <Left>netstandard2.1/netstandard.dll</Left>
    <Right>net9.0/netstandard.dll</Right>
  </Suppression>
  <Suppression>
    <DiagnosticId>CP0014</DiagnosticId>
    <Target>P:System.Diagnostics.ProcessStartInfo.CreateNoWindow:[T:System.ComponentModel.DefaultValueAttribute]</Target>
    <Left>netstandard2.1/netstandard.dll</Left>
    <Right>net9.0/netstandard.dll</Right>
  </Suppression>
  <Suppression>
    <DiagnosticId>CP0014</DiagnosticId>
    <Target>P:System.Diagnostics.ProcessStartInfo.CreateNoWindow:[T:System.ComponentModel.NotifyParentPropertyAttribute]</Target>
    <Left>netstandard2.1/netstandard.dll</Left>
    <Right>net9.0/netstandard.dll</Right>
  </Suppression>
  <Suppression>
    <DiagnosticId>CP0014</DiagnosticId>
    <Target>P:System.Diagnostics.ProcessStartInfo.Domain:[T:System.ComponentModel.NotifyParentPropertyAttribute]</Target>
    <Left>netstandard2.1/netstandard.dll</Left>
    <Right>net9.0/netstandard.dll</Right>
  </Suppression>
  <Suppression>
    <DiagnosticId>CP0014</DiagnosticId>
    <Target>P:System.Diagnostics.ProcessStartInfo.Environment:[T:System.ComponentModel.DefaultValueAttribute]</Target>
    <Left>netstandard2.1/netstandard.dll</Left>
    <Right>net9.0/netstandard.dll</Right>
  </Suppression>
  <Suppression>
    <DiagnosticId>CP0014</DiagnosticId>
    <Target>P:System.Diagnostics.ProcessStartInfo.Environment:[T:System.ComponentModel.DesignerSerializationVisibilityAttribute]</Target>
    <Left>netstandard2.1/netstandard.dll</Left>
    <Right>net9.0/netstandard.dll</Right>
  </Suppression>
  <Suppression>
    <DiagnosticId>CP0014</DiagnosticId>
    <Target>P:System.Diagnostics.ProcessStartInfo.Environment:[T:System.ComponentModel.NotifyParentPropertyAttribute]</Target>
    <Left>netstandard2.1/netstandard.dll</Left>
    <Right>net9.0/netstandard.dll</Right>
  </Suppression>
  <Suppression>
    <DiagnosticId>CP0014</DiagnosticId>
    <Target>P:System.Diagnostics.ProcessStartInfo.EnvironmentVariables:[T:System.ComponentModel.DefaultValueAttribute]</Target>
    <Left>netstandard2.1/netstandard.dll</Left>
    <Right>net9.0/netstandard.dll</Right>
  </Suppression>
  <Suppression>
    <DiagnosticId>CP0014</DiagnosticId>
    <Target>P:System.Diagnostics.ProcessStartInfo.EnvironmentVariables:[T:System.ComponentModel.DesignerSerializationVisibilityAttribute]</Target>
    <Left>netstandard2.1/netstandard.dll</Left>
    <Right>net9.0/netstandard.dll</Right>
  </Suppression>
  <Suppression>
    <DiagnosticId>CP0014</DiagnosticId>
    <Target>P:System.Diagnostics.ProcessStartInfo.EnvironmentVariables:[T:System.ComponentModel.NotifyParentPropertyAttribute]</Target>
    <Left>netstandard2.1/netstandard.dll</Left>
    <Right>net9.0/netstandard.dll</Right>
  </Suppression>
  <Suppression>
    <DiagnosticId>CP0014</DiagnosticId>
    <Target>P:System.Diagnostics.ProcessStartInfo.ErrorDialog:[T:System.ComponentModel.DefaultValueAttribute]</Target>
    <Left>netstandard2.1/netstandard.dll</Left>
    <Right>net9.0/netstandard.dll</Right>
  </Suppression>
  <Suppression>
    <DiagnosticId>CP0014</DiagnosticId>
    <Target>P:System.Diagnostics.ProcessStartInfo.ErrorDialog:[T:System.ComponentModel.NotifyParentPropertyAttribute]</Target>
    <Left>netstandard2.1/netstandard.dll</Left>
    <Right>net9.0/netstandard.dll</Right>
  </Suppression>
  <Suppression>
    <DiagnosticId>CP0014</DiagnosticId>
    <Target>P:System.Diagnostics.ProcessStartInfo.ErrorDialogParentHandle:[T:System.ComponentModel.BrowsableAttribute]</Target>
    <Left>netstandard2.1/netstandard.dll</Left>
    <Right>net9.0/netstandard.dll</Right>
  </Suppression>
  <Suppression>
    <DiagnosticId>CP0014</DiagnosticId>
    <Target>P:System.Diagnostics.ProcessStartInfo.ErrorDialogParentHandle:[T:System.ComponentModel.DesignerSerializationVisibilityAttribute]</Target>
    <Left>netstandard2.1/netstandard.dll</Left>
    <Right>net9.0/netstandard.dll</Right>
  </Suppression>
  <Suppression>
    <DiagnosticId>CP0014</DiagnosticId>
    <Target>P:System.Diagnostics.ProcessStartInfo.FileName:[T:System.ComponentModel.DefaultValueAttribute]</Target>
    <Left>netstandard2.1/netstandard.dll</Left>
    <Right>net9.0/netstandard.dll</Right>
  </Suppression>
  <Suppression>
    <DiagnosticId>CP0014</DiagnosticId>
    <Target>P:System.Diagnostics.ProcessStartInfo.FileName:[T:System.ComponentModel.NotifyParentPropertyAttribute]</Target>
    <Left>netstandard2.1/netstandard.dll</Left>
    <Right>net9.0/netstandard.dll</Right>
  </Suppression>
  <Suppression>
    <DiagnosticId>CP0014</DiagnosticId>
    <Target>P:System.Diagnostics.ProcessStartInfo.FileName:[T:System.ComponentModel.SettingsBindableAttribute]</Target>
    <Left>netstandard2.1/netstandard.dll</Left>
    <Right>net9.0/netstandard.dll</Right>
  </Suppression>
  <Suppression>
    <DiagnosticId>CP0014</DiagnosticId>
    <Target>P:System.Diagnostics.ProcessStartInfo.LoadUserProfile:[T:System.ComponentModel.NotifyParentPropertyAttribute]</Target>
    <Left>netstandard2.1/netstandard.dll</Left>
    <Right>net9.0/netstandard.dll</Right>
  </Suppression>
  <Suppression>
    <DiagnosticId>CP0014</DiagnosticId>
    <Target>P:System.Diagnostics.ProcessStartInfo.PasswordInClearText:[T:System.ComponentModel.BrowsableAttribute]</Target>
    <Left>netstandard2.1/netstandard.dll</Left>
    <Right>net9.0/netstandard.dll</Right>
  </Suppression>
  <Suppression>
    <DiagnosticId>CP0014</DiagnosticId>
    <Target>P:System.Diagnostics.ProcessStartInfo.PasswordInClearText:[T:System.ComponentModel.DesignerSerializationVisibilityAttribute]</Target>
    <Left>netstandard2.1/netstandard.dll</Left>
    <Right>net9.0/netstandard.dll</Right>
  </Suppression>
  <Suppression>
    <DiagnosticId>CP0014</DiagnosticId>
    <Target>P:System.Diagnostics.ProcessStartInfo.RedirectStandardError:[T:System.ComponentModel.DefaultValueAttribute]</Target>
    <Left>netstandard2.1/netstandard.dll</Left>
    <Right>net9.0/netstandard.dll</Right>
  </Suppression>
  <Suppression>
    <DiagnosticId>CP0014</DiagnosticId>
    <Target>P:System.Diagnostics.ProcessStartInfo.RedirectStandardError:[T:System.ComponentModel.NotifyParentPropertyAttribute]</Target>
    <Left>netstandard2.1/netstandard.dll</Left>
    <Right>net9.0/netstandard.dll</Right>
  </Suppression>
  <Suppression>
    <DiagnosticId>CP0014</DiagnosticId>
    <Target>P:System.Diagnostics.ProcessStartInfo.RedirectStandardInput:[T:System.ComponentModel.DefaultValueAttribute]</Target>
    <Left>netstandard2.1/netstandard.dll</Left>
    <Right>net9.0/netstandard.dll</Right>
  </Suppression>
  <Suppression>
    <DiagnosticId>CP0014</DiagnosticId>
    <Target>P:System.Diagnostics.ProcessStartInfo.RedirectStandardInput:[T:System.ComponentModel.NotifyParentPropertyAttribute]</Target>
    <Left>netstandard2.1/netstandard.dll</Left>
    <Right>net9.0/netstandard.dll</Right>
  </Suppression>
  <Suppression>
    <DiagnosticId>CP0014</DiagnosticId>
    <Target>P:System.Diagnostics.ProcessStartInfo.RedirectStandardOutput:[T:System.ComponentModel.DefaultValueAttribute]</Target>
    <Left>netstandard2.1/netstandard.dll</Left>
    <Right>net9.0/netstandard.dll</Right>
  </Suppression>
  <Suppression>
    <DiagnosticId>CP0014</DiagnosticId>
    <Target>P:System.Diagnostics.ProcessStartInfo.RedirectStandardOutput:[T:System.ComponentModel.NotifyParentPropertyAttribute]</Target>
    <Left>netstandard2.1/netstandard.dll</Left>
    <Right>net9.0/netstandard.dll</Right>
  </Suppression>
  <Suppression>
    <DiagnosticId>CP0014</DiagnosticId>
    <Target>P:System.Diagnostics.ProcessStartInfo.UserName:[T:System.ComponentModel.NotifyParentPropertyAttribute]</Target>
    <Left>netstandard2.1/netstandard.dll</Left>
    <Right>net9.0/netstandard.dll</Right>
  </Suppression>
  <Suppression>
    <DiagnosticId>CP0014</DiagnosticId>
    <Target>P:System.Diagnostics.ProcessStartInfo.UseShellExecute:[T:System.ComponentModel.DefaultValueAttribute]</Target>
    <Left>netstandard2.1/netstandard.dll</Left>
    <Right>net9.0/netstandard.dll</Right>
  </Suppression>
  <Suppression>
    <DiagnosticId>CP0014</DiagnosticId>
    <Target>P:System.Diagnostics.ProcessStartInfo.UseShellExecute:[T:System.ComponentModel.NotifyParentPropertyAttribute]</Target>
    <Left>netstandard2.1/netstandard.dll</Left>
    <Right>net9.0/netstandard.dll</Right>
  </Suppression>
  <Suppression>
    <DiagnosticId>CP0014</DiagnosticId>
    <Target>P:System.Diagnostics.ProcessStartInfo.Verb:[T:System.ComponentModel.NotifyParentPropertyAttribute]</Target>
    <Left>netstandard2.1/netstandard.dll</Left>
    <Right>net9.0/netstandard.dll</Right>
  </Suppression>
  <Suppression>
    <DiagnosticId>CP0014</DiagnosticId>
    <Target>P:System.Diagnostics.ProcessStartInfo.Verbs:[T:System.ComponentModel.BrowsableAttribute]</Target>
    <Left>netstandard2.1/netstandard.dll</Left>
    <Right>net9.0/netstandard.dll</Right>
  </Suppression>
  <Suppression>
    <DiagnosticId>CP0014</DiagnosticId>
    <Target>P:System.Diagnostics.ProcessStartInfo.Verbs:[T:System.ComponentModel.DesignerSerializationVisibilityAttribute]</Target>
    <Left>netstandard2.1/netstandard.dll</Left>
    <Right>net9.0/netstandard.dll</Right>
  </Suppression>
  <Suppression>
    <DiagnosticId>CP0014</DiagnosticId>
    <Target>P:System.Diagnostics.ProcessStartInfo.WindowStyle:[T:System.ComponentModel.NotifyParentPropertyAttribute]</Target>
    <Left>netstandard2.1/netstandard.dll</Left>
    <Right>net9.0/netstandard.dll</Right>
  </Suppression>
  <Suppression>
    <DiagnosticId>CP0014</DiagnosticId>
    <Target>P:System.Diagnostics.ProcessStartInfo.WorkingDirectory:[T:System.ComponentModel.DefaultValueAttribute]</Target>
    <Left>netstandard2.1/netstandard.dll</Left>
    <Right>net9.0/netstandard.dll</Right>
  </Suppression>
  <Suppression>
    <DiagnosticId>CP0014</DiagnosticId>
    <Target>P:System.Diagnostics.ProcessStartInfo.WorkingDirectory:[T:System.ComponentModel.NotifyParentPropertyAttribute]</Target>
    <Left>netstandard2.1/netstandard.dll</Left>
    <Right>net9.0/netstandard.dll</Right>
  </Suppression>
  <Suppression>
    <DiagnosticId>CP0014</DiagnosticId>
    <Target>P:System.Diagnostics.ProcessStartInfo.WorkingDirectory:[T:System.ComponentModel.SettingsBindableAttribute]</Target>
    <Left>netstandard2.1/netstandard.dll</Left>
    <Right>net9.0/netstandard.dll</Right>
  </Suppression>
  <Suppression>
    <DiagnosticId>CP0014</DiagnosticId>
    <Target>P:System.Diagnostics.ProcessThread.IdealProcessor:[T:System.ComponentModel.BrowsableAttribute]</Target>
    <Left>netstandard2.1/netstandard.dll</Left>
    <Right>net9.0/netstandard.dll</Right>
  </Suppression>
  <Suppression>
    <DiagnosticId>CP0014</DiagnosticId>
    <Target>P:System.Diagnostics.ProcessThread.ProcessorAffinity:[T:System.ComponentModel.BrowsableAttribute]</Target>
    <Left>netstandard2.1/netstandard.dll</Left>
    <Right>net9.0/netstandard.dll</Right>
  </Suppression>
  <Suppression>
    <DiagnosticId>CP0014</DiagnosticId>
    <Target>P:System.IO.FileSystemWatcher.EnableRaisingEvents:[T:System.ComponentModel.DefaultValueAttribute]</Target>
    <Left>netstandard2.1/netstandard.dll</Left>
    <Right>net9.0/netstandard.dll</Right>
  </Suppression>
  <Suppression>
    <DiagnosticId>CP0014</DiagnosticId>
    <Target>P:System.IO.FileSystemWatcher.Filter:[T:System.ComponentModel.DefaultValueAttribute]</Target>
    <Left>netstandard2.1/netstandard.dll</Left>
    <Right>net9.0/netstandard.dll</Right>
  </Suppression>
  <Suppression>
    <DiagnosticId>CP0014</DiagnosticId>
    <Target>P:System.IO.FileSystemWatcher.Filter:[T:System.ComponentModel.SettingsBindableAttribute]</Target>
    <Left>netstandard2.1/netstandard.dll</Left>
    <Right>net9.0/netstandard.dll</Right>
  </Suppression>
  <Suppression>
    <DiagnosticId>CP0014</DiagnosticId>
    <Target>P:System.IO.FileSystemWatcher.IncludeSubdirectories:[T:System.ComponentModel.DefaultValueAttribute]</Target>
    <Left>netstandard2.1/netstandard.dll</Left>
    <Right>net9.0/netstandard.dll</Right>
  </Suppression>
  <Suppression>
    <DiagnosticId>CP0014</DiagnosticId>
    <Target>P:System.IO.FileSystemWatcher.InternalBufferSize:[T:System.ComponentModel.BrowsableAttribute]</Target>
    <Left>netstandard2.1/netstandard.dll</Left>
    <Right>net9.0/netstandard.dll</Right>
  </Suppression>
  <Suppression>
    <DiagnosticId>CP0014</DiagnosticId>
    <Target>P:System.IO.FileSystemWatcher.InternalBufferSize:[T:System.ComponentModel.DefaultValueAttribute]</Target>
    <Left>netstandard2.1/netstandard.dll</Left>
    <Right>net9.0/netstandard.dll</Right>
  </Suppression>
  <Suppression>
    <DiagnosticId>CP0014</DiagnosticId>
    <Target>P:System.IO.FileSystemWatcher.NotifyFilter:[T:System.ComponentModel.DefaultValueAttribute]</Target>
    <Left>netstandard2.1/netstandard.dll</Left>
    <Right>net9.0/netstandard.dll</Right>
  </Suppression>
  <Suppression>
    <DiagnosticId>CP0014</DiagnosticId>
    <Target>P:System.IO.FileSystemWatcher.Path:[T:System.ComponentModel.DefaultValueAttribute]</Target>
    <Left>netstandard2.1/netstandard.dll</Left>
    <Right>net9.0/netstandard.dll</Right>
  </Suppression>
  <Suppression>
    <DiagnosticId>CP0014</DiagnosticId>
    <Target>P:System.IO.FileSystemWatcher.Path:[T:System.ComponentModel.SettingsBindableAttribute]</Target>
    <Left>netstandard2.1/netstandard.dll</Left>
    <Right>net9.0/netstandard.dll</Right>
  </Suppression>
  <Suppression>
    <DiagnosticId>CP0014</DiagnosticId>
    <Target>P:System.IO.FileSystemWatcher.Site:[T:System.ComponentModel.BrowsableAttribute]</Target>
    <Left>netstandard2.1/netstandard.dll</Left>
    <Right>net9.0/netstandard.dll</Right>
  </Suppression>
  <Suppression>
    <DiagnosticId>CP0014</DiagnosticId>
    <Target>P:System.IO.FileSystemWatcher.SynchronizingObject:[T:System.ComponentModel.BrowsableAttribute]</Target>
    <Left>netstandard2.1/netstandard.dll</Left>
    <Right>net9.0/netstandard.dll</Right>
  </Suppression>
  <Suppression>
    <DiagnosticId>CP0014</DiagnosticId>
    <Target>P:System.IO.FileSystemWatcher.SynchronizingObject:[T:System.ComponentModel.DefaultValueAttribute]</Target>
    <Left>netstandard2.1/netstandard.dll</Left>
    <Right>net9.0/netstandard.dll</Right>
  </Suppression>
  <Suppression>
    <DiagnosticId>CP0014</DiagnosticId>
    <Target>P:System.Timers.Timer.AutoReset:[T:System.ComponentModel.CategoryAttribute]</Target>
    <Left>netstandard2.1/netstandard.dll</Left>
    <Right>net9.0/netstandard.dll</Right>
  </Suppression>
  <Suppression>
    <DiagnosticId>CP0014</DiagnosticId>
    <Target>P:System.Timers.Timer.Enabled:[T:System.ComponentModel.CategoryAttribute]</Target>
    <Left>netstandard2.1/netstandard.dll</Left>
    <Right>net9.0/netstandard.dll</Right>
  </Suppression>
  <Suppression>
    <DiagnosticId>CP0014</DiagnosticId>
    <Target>P:System.Timers.Timer.Interval:[T:System.ComponentModel.CategoryAttribute]</Target>
    <Left>netstandard2.1/netstandard.dll</Left>
    <Right>net9.0/netstandard.dll</Right>
  </Suppression>
  <Suppression>
    <DiagnosticId>CP0014</DiagnosticId>
    <Target>P:System.Timers.Timer.Interval:[T:System.ComponentModel.SettingsBindableAttribute]</Target>
    <Left>netstandard2.1/netstandard.dll</Left>
    <Right>net9.0/netstandard.dll</Right>
  </Suppression>
  <Suppression>
    <DiagnosticId>CP0014</DiagnosticId>
    <Target>P:System.Timers.Timer.SynchronizingObject:[T:System.ComponentModel.BrowsableAttribute]</Target>
    <Left>netstandard2.1/netstandard.dll</Left>
    <Right>net9.0/netstandard.dll</Right>
  </Suppression>
  <Suppression>
    <DiagnosticId>CP0014</DiagnosticId>
    <Target>T:System.ComponentModel.BackgroundWorker:[T:System.ComponentModel.DefaultEventAttribute]</Target>
    <Left>netstandard2.1/netstandard.dll</Left>
    <Right>net9.0/netstandard.dll</Right>
  </Suppression>
  <Suppression>
    <DiagnosticId>CP0014</DiagnosticId>
    <Target>T:System.Diagnostics.Process:[T:System.ComponentModel.DefaultEventAttribute]</Target>
    <Left>netstandard2.1/netstandard.dll</Left>
    <Right>net9.0/netstandard.dll</Right>
  </Suppression>
  <Suppression>
    <DiagnosticId>CP0014</DiagnosticId>
    <Target>T:System.Diagnostics.Process:[T:System.ComponentModel.DefaultPropertyAttribute]</Target>
    <Left>netstandard2.1/netstandard.dll</Left>
    <Right>net9.0/netstandard.dll</Right>
  </Suppression>
  <Suppression>
    <DiagnosticId>CP0014</DiagnosticId>
    <Target>T:System.IO.FileSystemWatcher:[T:System.ComponentModel.DefaultEventAttribute]</Target>
    <Left>netstandard2.1/netstandard.dll</Left>
    <Right>net9.0/netstandard.dll</Right>
  </Suppression>
  <Suppression>
    <DiagnosticId>CP0015</DiagnosticId>
    <Target>P:System.Timers.Timer.Interval:[T:System.ComponentModel.DefaultValueAttribute]</Target>
    <Left>netstandard2.1/netstandard.dll</Left>
    <Right>net9.0/netstandard.dll</Right>
  </Suppression>
  <Suppression>
    <DiagnosticId>CP0015</DiagnosticId>
    <Target>T:System.Runtime.CompilerServices.AsyncMethodBuilderAttribute:[T:System.AttributeUsageAttribute]</Target>
    <Left>netstandard2.1/netstandard.dll</Left>
    <Right>net9.0/netstandard.dll</Right>
  </Suppression>
  <Suppression>
    <DiagnosticId>CP0015</DiagnosticId>
    <Target>T:System.Runtime.InteropServices.ManagedToNativeComInteropStubAttribute:[T:System.AttributeUsageAttribute]</Target>
    <Left>netstandard2.1/netstandard.dll</Left>
    <Right>net9.0/netstandard.dll</Right>
  </Suppression>
  <Suppression>
    <DiagnosticId>CP0015</DiagnosticId>
    <Target>T:System.Xml.Serialization.XmlAnyAttributeAttribute:[T:System.AttributeUsageAttribute]</Target>
    <Left>netstandard2.1/netstandard.dll</Left>
    <Right>net9.0/netstandard.dll</Right>
  </Suppression>
  <Suppression>
    <DiagnosticId>CP0015</DiagnosticId>
    <Target>T:System.Xml.Serialization.XmlNamespaceDeclarationsAttribute:[T:System.AttributeUsageAttribute]</Target>
    <Left>netstandard2.1/netstandard.dll</Left>
    <Right>net9.0/netstandard.dll</Right>
  </Suppression>
</Suppressions>