{
    "Version" : "1.0.0",
    "AuthenticationType" : "AAD_CERT",
    "TenantId" : "975f013f-7f24-47e8-a7d3-abc4752bf346",
    "ClientId" : "22346933-af99-4e94-97d5-7fa1dcf4bba6",
    "AuthCert" :
    {
        "SubjectName" : "CN=22346933-af99-4e94-97d5-7fa1dcf4bba6.microsoft.com",
        "StoreLocation" : "CurrentUser",
        "StoreName": "My",
        "SendX5c" : "true",
        "WithAzureRegion": false
    },
    "RequestSigningCert" :
    {
        "GetCertFromKeyVault" : true,
        "KeyVaultName": "clrdiag-esrp-pme",
        "KeyVaultCertName": "dac-dnceng-esrpclient-cert",
        "SendX5c": false,
        "WithAzureRegion": false
    },
    "OAuthToken": null
}
