<?xml version="1.0" encoding="utf-8"?>
<Suppressions xmlns:xsi="http://www.w3.org/2001/XMLSchema-instance" xmlns:xsd="http://www.w3.org/2001/XMLSchema">
  <Suppression>
    <DiagnosticId>CP0020</DiagnosticId>
    <Target>M:System.ComponentModel.AttributeCollection.get_Attributes</Target>
    <Left>ref/net7.0/System.ComponentModel.TypeConverter.dll</Left>
    <Right>lib/net7.0/System.ComponentModel.TypeConverter.dll</Right>
  </Suppression>
  <Suppression>
    <DiagnosticId>CP0020</DiagnosticId>
    <Target>P:System.ComponentModel.AttributeCollection.Attributes</Target>
    <Left>ref/net7.0/System.ComponentModel.TypeConverter.dll</Left>
    <Right>lib/net7.0/System.ComponentModel.TypeConverter.dll</Right>
  </Suppression>
</Suppressions>