<?xml version="1.0" encoding="utf-8"?>
<!-- https://learn.microsoft.com/en-us/dotnet/fundamentals/package-validation/diagnostic-ids -->
<Suppressions xmlns:xsi="http://www.w3.org/2001/XMLSchema-instance" xmlns:xsd="http://www.w3.org/2001/XMLSchema">
  <Suppression>
    <DiagnosticId>CP0001</DiagnosticId>
    <Target>T:Internal.Console</Target>
  </Suppression>
  <Suppression>
    <DiagnosticId>CP0001</DiagnosticId>
    <Target>T:System.Runtime.CompilerServices.ICastable</Target>
  </Suppression>
  <Suppression>
    <DiagnosticId>CP0002</DiagnosticId>
    <Target>F:System.Resources.ResourceManager.BaseNameField</Target>
  </Suppression>
  <Suppression>
    <DiagnosticId>CP0002</DiagnosticId>
    <Target>F:System.Resources.ResourceSet.Reader</Target>
  </Suppression>
  <Suppression>
    <DiagnosticId>CP0002</DiagnosticId>
    <Target>M:System.Threading.ThreadPool.BindHandlePortableCore(System.IntPtr)</Target>
    <Left>ref/net8.0/System.Private.CoreLib.dll</Left>
    <Right>lib/net8.0/System.Private.CoreLib.dll</Right>
  </Suppression>
  <Suppression>
    <DiagnosticId>CP0002</DiagnosticId>
    <Target>M:System.Threading.ThreadPool.BindHandlePortableCore(System.Runtime.InteropServices.SafeHandle)</Target>
    <Left>ref/net8.0/System.Private.CoreLib.dll</Left>
    <Right>lib/net8.0/System.Private.CoreLib.dll</Right>
  </Suppression>
  <Suppression>
    <DiagnosticId>CP0002</DiagnosticId>
    <Target>M:System.Threading.ThreadPool.UnsafeQueueNativeOverlappedPortableCore(System.Threading.NativeOverlapped*)</Target>
    <Left>ref/net8.0/System.Private.CoreLib.dll</Left>
    <Right>lib/net8.0/System.Private.CoreLib.dll</Right>
  </Suppression>
  <Suppression>
    <DiagnosticId>CP0014</DiagnosticId>
    <Target>M:System.Runtime.CompilerServices.RuntimeHelpers.GetObjectValue(System.Object)-&gt;object?:[T:System.Diagnostics.CodeAnalysis.NotNullIfNotNullAttribute]</Target>
  </Suppression>
  <Suppression>
    <DiagnosticId>CP0014</DiagnosticId>
    <Target>M:System.Runtime.InteropServices.Marshal.CreateWrapperOfType(System.Object,System.Type)-&gt;object?:[T:System.Diagnostics.CodeAnalysis.NotNullIfNotNullAttribute]</Target>
  </Suppression>
</Suppressions>