<?xml version="1.0" encoding="utf-8"?>
<Dependencies>
  <ProductDependencies>
    <Dependency Name="Microsoft.Private.CoreFx.NETCoreApp" Version="4.6.0-preview6.19225.6">
      <Uri>https://github.com/dotnet/corefx</Uri>
      <Sha>3662c77596167ac2393fed6fb3dd9416446f36d2</Sha>
    </Dependency>
    <Dependency Name="Microsoft.NETCore.Platforms" Version="3.0.0-preview6.19225.6">
      <Uri>https://github.com/dotnet/corefx</Uri>
      <Sha>3662c77596167ac2393fed6fb3dd9416446f36d2</Sha>
    </Dependency>
    <Dependency Name="Microsoft.NETCore.Targets" Version="2.0.0" Pinned="true">
      <Uri>https://github.com/dotnet/corefx</Uri>
      <Sha>8321c729934c0f8be754953439b88e6e1c120c24</Sha>
    </Dependency>
    <Dependency Name="NETStandard.Library" Version="2.1.0-prerelease.19226.1">
      <Uri>https://github.com/dotnet/standard</Uri>
      <Sha>4acc9a6f8f71debcb1d93a4cd66b5c769e998e4e</Sha>
    </Dependency>
    <Dependency Name="Microsoft.NETCore.Runtime.CoreCLR" Version="3.0.0-preview6-27624-71">
      <Uri>https://github.com/dotnet/coreclr</Uri>
      <Sha>8808f4eab10d1760182590cad4964f566b9c88ca</Sha>
    </Dependency>
    <Dependency Name="Microsoft.Private.WindowsDesktop.App" Version="3.0.0-preview6-27626-16">
      <Uri>https://dev.azure.com/devdiv/DevDiv/_git/DotNet-Trusted</Uri>
      <Sha>99f473e7a600adf7e7fcbc1b91cef9e61d3d54da</Sha>
    </Dependency>
  </ProductDependencies>
  <ToolsetDependencies>
    <Dependency Name="Microsoft.DotNet.Arcade.Sdk" Version="1.0.0-beta.19225.5">
      <Uri>https://github.com/dotnet/arcade</Uri>
      <Sha>d37270268a65592cae630f1b979b70f74d4614dd</Sha>
    </Dependency>
  </ToolsetDependencies>
</Dependencies>
