<?xml version="1.0" encoding="utf-8"?>
<Dependencies>
  <ProductDependencies>
    <Dependency Name="Microsoft.Private.CoreFx.NETCoreApp" Version="4.6.0-preview6.19259.4">
      <Uri>https://github.com/dotnet/corefx</Uri>
      <Sha>e72c6c53baddb02a630e8e6592a59d89e30b856b</Sha>
    </Dependency>
    <Dependency Name="Microsoft.NETCore.Platforms" Version="3.0.0-preview6.19259.4">
      <Uri>https://github.com/dotnet/corefx</Uri>
      <Sha>e72c6c53baddb02a630e8e6592a59d89e30b856b</Sha>
    </Dependency>
    <Dependency Name="Microsoft.NETCore.Targets" Version="2.0.0" Pinned="true">
      <Uri>https://github.com/dotnet/corefx</Uri>
      <Sha>8321c729934c0f8be754953439b88e6e1c120c24</Sha>
    </Dependency>
    <Dependency Name="NETStandard.Library" Version="2.1.0-prerelease.19259.7">
      <Uri>https://github.com/dotnet/standard</Uri>
      <Sha>013b89db06c1f331804d2c07c79c9b5192b3c5d7</Sha>
    </Dependency>
    <Dependency Name="Microsoft.NETCore.Runtime.CoreCLR" Version="3.0.0-preview6-27708-71">
      <Uri>https://github.com/dotnet/coreclr</Uri>
      <Sha>794f2f89399026246562181bc999a5027fb6583d</Sha>
    </Dependency>
    <Dependency Name="Microsoft.Private.WindowsDesktop.App" Version="3.0.0-preview6-27709-8">
      <Uri>https://dev.azure.com/devdiv/DevDiv/_git/DotNet-Trusted</Uri>
      <Sha>3340c843c2b54f7166e88bd52c3dc632b4c9272f</Sha>
    </Dependency>
  </ProductDependencies>
  <ToolsetDependencies>
    <Dependency Name="Microsoft.DotNet.Arcade.Sdk" Version="1.0.0-beta.19255.2">
      <Uri>https://github.com/dotnet/arcade</Uri>
      <Sha>6a34948f7bdbc3ceb2fb16441b49f7748a462646</Sha>
    </Dependency>
  </ToolsetDependencies>
</Dependencies>
