<?xml version="1.0" encoding="utf-8"?>
<Dependencies>
  <ProductDependencies>
    <Dependency Name="Microsoft.Private.CoreFx.NETCoreApp" Version="4.6.0-preview4.19164.7">
      <Uri>https://github.com/dotnet/corefx</Uri>
      <Sha>d6a30736858f91b297fdd3ed4e3d1dfde67bdbdb</Sha>
    </Dependency>
    <Dependency Name="Microsoft.NETCore.Platforms" Version="3.0.0-preview4.19164.7">
      <Uri>https://github.com/dotnet/corefx</Uri>
      <Sha>d6a30736858f91b297fdd3ed4e3d1dfde67bdbdb</Sha>
    </Dependency>
    <PinnedDependency Name="Microsoft.NETCore.Targets" Version="2.0.0">
      <Uri>https://github.com/dotnet/corefx</Uri>
    </PinnedDependency>
    <PinnedDependency Name="NETStandard.Library" Version="2.0.3">
      <Uri>https://github.com/dotnet/standard</Uri>
    </PinnedDependency>
    <Dependency Name="Microsoft.NETCore.Runtime.CoreCLR" Version="3.0.0-preview4-27522-71">
      <Uri>https://github.com/dotnet/coreclr</Uri>
      <Sha>5d57b87227b7fd116735edf9f5f75b3154953d8e</Sha>
    </Dependency>
    <Dependency Name="Microsoft.WindowsDesktop.App" Version="3.0.0-preview4-27520-2">
      <Uri>https://dev.azure.com/devdiv/DevDiv/_git/DotNet-Trusted</Uri>
      <Sha>9af484c80173bd7769f85fc3b1a6539d9731ef4f</Sha>
    </Dependency>
  </ProductDependencies>
  <ToolsetDependencies>
    <Dependency Name="Microsoft.DotNet.Arcade.Sdk" Version="1.0.0-beta.19171.3">
      <Uri>https://github.com/dotnet/arcade</Uri>
      <Sha>b3bcf3034ff395bd09066114379ec64736b13633</Sha>
    </Dependency>
  </ToolsetDependencies>
</Dependencies>
